README.md
setup.cfg
setup.py
nothing_matrix_calculator.egg-info/PKG-INFO
nothing_matrix_calculator.egg-info/SOURCES.txt
nothing_matrix_calculator.egg-info/dependency_links.txt
nothing_matrix_calculator.egg-info/top_level.txt
utils/__init__.py
utils/executor.py
utils/matrix.py