Metadata-Version: 1.1
Name: nothing-matrix-calculator
Version: 0.0.3
Summary: Matrix Calculator
Home-page: https://github.com/nothing2512/matrix-calculator
Author: Robet Atiq Maulana Rifqi
Author-email: blank345red@gmail.com
License: MIT
Download-URL: https://github.com/nothing2512/matrix-calculator/archive/refs/tags/0.0.3.zip
Keywords: MATRIX,MATRICE,CALCULATOR
Platform: UNKNOWN
